datascifuncs/__init__.py
datascifuncs/build_pipeline.py
datascifuncs/data_viz_formatting.py
datascifuncs/metrics.py
datascifuncs/reset_project.py
datascifuncs/tools.py
tests/__init__.py
tests/test_metrics.py
tests/test_reset_project.py
tests/test_tools.py
datascifuncs-0.1.5.dist-info/LICENSE
datascifuncs-0.1.5.dist-info/METADATA
datascifuncs-0.1.5.dist-info/WHEEL
datascifuncs-0.1.5.dist-info/entry_points.txt
datascifuncs-0.1.5.dist-info/top_level.txt
datascifuncs-0.1.5.dist-info/RECORD
