Metadata-Version: 2.2
Name: datascifuncs
Version: 0.1.5
Summary: A package for loading/saving data and verifying paths.
Home-page: https://github.com/dlumian/DataSciFuncs
Author: Danny Lumian
Author-email: dlumian@gmail.com
Classifier: Programming Language :: Python :: 3
Classifier: License :: OSI Approved :: MIT License
Classifier: Operating System :: OS Independent
Requires-Python: >=3.8
License-File: LICENSE
Requires-Dist: requests
Requires-Dist: pandas
Requires-Dist: seaborn
Requires-Dist: matplotlib
Requires-Dist: scikit-learn
Requires-Dist: nbconvert
Requires-Dist: nbformat
Dynamic: author
Dynamic: author-email
Dynamic: classifier
Dynamic: description
Dynamic: description-content-type
Dynamic: home-page
Dynamic: requires-dist
Dynamic: requires-python
Dynamic: summary
